[{"TOP":"","이름":"El(1)","무기장착시":"+50 To Attack Rating, +1 Light Radius","기타 장착시":"+15 Defense, +1 To Light Radius","룬업그레이드":"","큐브조합 사용":"칩보석과 함께 크루드등을 노멀방어구로","쓰이는 룬워드 아이템":"명예(Honor)","":""},{"TOP":"","이름":"Eld(2)","무기장착시":"+75% Damage To Undead, +50 Attack Rating Against Undead","기타 장착시":"15% Slower Stamina D비 (Rain)/7% Increased Chance of Blocking(Shields)","룬업그레이드":"3*El","큐브조합 사용":"칩보석과 함께 크루드등을 노멀무기로","쓰이는 룬워드 아이템":"침묵(Silence)","":""},{"TOP":"","이름":"Tir(3)","무기장착시":"+2 To Mana After Each Kill","기타 장착시":"+2 To Mana After Each Kill","룬업그레이드":"3*Eld","큐브조합 사용":"","쓰이는 룬워드 아이템":"명예(Honor)","":"통찰력 (Insight)"},{"TOP":"","이름":"Nef(4)","무기장착시":"Knockback","기타 장착시":"+30 Defense Vs. Missile","룬업그레이드":"3*Tir","큐브조합 사용":"","쓰이는 룬워드 아이템":"블랙(Black)","":""},{"TOP":"","이름":"Eth(5)","무기장착시":"-25% To Target Defense","기타 장착시":"Regenerate Mana 15%","룬업그레이드":"3*Nef","큐브조합 사용":"","쓰이는 룬워드 아이템":"원한(Fury)","":""},{"TOP":"","이름":"Ith(6)","무기장착시":"+9 To Maximum Damage","기타 장착시":"15% Damage Taken Goes to Mana","룬업그레이드":"3*Eth","큐브조합 사용":"","쓰이는 룬워드 아이템":"명예(Honor)","":""},{"TOP":"","이름":"Tal(7)","무기장착시":"+75 Poison Damage Over 5 Seconds","기타 장착시":"Poison Resist 30%/Poison Resist 35%(Shields)","룬업그레이드":"3*Ith","큐브조합 사용":"노멀 갑옷/방패 소켓 생성                    노멀 유니크 방어구 업글","쓰이는 룬워드 아이템":"고대인의 서약(Ancient's Pledge)","":""},{"TOP":"","이름":"Ral(8)","무기장착시":"Adds 5-30 Fire Damage","기타 장착시":"Fire Resist 30%/Fire Resist 35%(Shields)","룬업그레이드":"3*Tal","큐브조합 사용":"방어구 수리, 노멀 무기/헬름 소켓 생성 노멀 유니크무기/노멀레어방어구 업글","쓰이는 룬워드 아이템":"고대인의 서약(Ancient's Pledge)","":""},{"TOP":"","이름":"Ort(9)","무기장착시":"Adds 1-50 Lightning Damage","기타 장착시":"Lightning Resist 30%/Lightning Resist 35%(Shields)","룬업그레이드":"3*Ral","큐브조합 사용":"노멀 레어 방어구 업글                        무기 수리(+최하급보석)","쓰이는 룬워드 아이템":"고대인의 서약(Ancient's Pledge)","":""},{"TOP":"","이름":"Thul(10)","무기장착시":"Adds 3-14 Cold Damage - 3 Second Duration","기타 장착시":"Cold Resist 30%/Cold Resist 35%(Shields)","룬업그레이드":"3*Ort","큐브조합 사용":"노멀 갑옷/헬름 소켓 생성,    노멀 레어 방어구 업글(Ral + 최상급 자수정)","쓰이는 룬워드 아이템":"블랙(Black)","":""},{"TOP":"","이름":"Amn(11)","무기장착시":"7% Life Stolen Per Hit","기타 장착시":"Attacker Takes Damage of 14","룬업그레이드":"3*Thul + 최하급 토파즈","큐브조합 사용":"노멀 무기/방패 소켓 생성,    노멀 레어 무기 업글(Ort + 최상급 사파이어)","쓰이는 룬워드 아이템":"명예(Honor)","":""},{"TOP":"","이름":"Sol(12)","무기장착시":"+9 To Minimum Damage","기타 장착시":"Damage Reduced By 7","룬업그레이드":"3*Amn + 최하급자수정","큐브조합 사용":"노멀 유니크 무기 업글(Ral + 최상급     에메랄드)","쓰이는 룬워드 아이템":"명예(Honor)","":""},{"TOP":"","이름":"Shael(13)","무기장착시":"20% Increased Attack Speed","기타 장착시":"20% Faster Hit Recovery/20% Faster Block Rate(Shields)","룬업그레이드":"3*Sol + 최하급 사파이어","큐브조합 사용":"노멀 유니크 방어구 업글(Tal + 최상급 다이아몬드)","쓰이는 룬워드 아이템":"멜로디(Melody)","":""},{"TOP":"","이름":"Dol(14)","무기장착시":"Hit Causes Monster To Flee 25%","기타 장착시":"Replenish Life +7","룬업그레이드":"3*Shael + 최하급 루비","큐브조합 사용":"","쓰이는 룬워드 아이템":"침묵(Silence)","":""},{"TOP":"","이름":"Hel(15)","무기장착시":"Requirements -20%","기타 장착시":"Requirements -15%","룬업그레이드":"3*Dol + 최하급 에메랄드","큐브조합 사용":"타운스크롤과 함께 소켓비우기","쓰이는 룬워드 아이템":"용맹한 자(Lionheart)","":""},{"TOP":"","이름":"Io(16)","무기장착시":"+10 To Vitality","기타 장착시":"+10 To Vitality","룬업그레이드":"3*Hel + 최하급 다이아몬드","큐브조합 사용":"","쓰이는 룬워드 아이템":"블랙(Black)","":""},{"TOP":"","이름":"Lum(17)","무기장착시":"+10 To Energy","기타 장착시":"+10 To Energy","룬업그레이드":"3*Io + 하급 토파즈","큐브조합 사용":"익셉유니크무기 업글(Pul+최상급 에메랄드)","쓰이는 룬워드 아이템":"용맹한 자(Lionheart)","":""},{"TOP":"","이름":"Ko(18)","무기장착시":"+10 To Dexterity","기타 장착시":"+10 To Dexterity","룬업그레이드":"3*Lum + 하급 자수정","큐브조합 사용":"익셉레어방어구업글(Pul+최상급 자수정) 익셉유니크방어구 업글","쓰이는 룬워드 아이템":"멜로디(Melody)","":""},{"TOP":"","이름":"Fal(19)","무기장착시":"+10 To 스트렝쓰(Strength)","기타 장착시":"+10 To 스트렝쓰(Strength)","룬업그레이드":"3*Ko + 하급 사파이어","큐브조합 사용":"익셉 레어 무기 업글(Um+최상급 사파이어)","쓰이는 룬워드 아이템":"용맹한 자(Lionheart)","":""},{"TOP":"","이름":"Lem(20)","무기장착시":"75% Extra Gold From Monsters","기타 장착시":"50% Extra Gold From Monsters","룬업그레이드":"3*Fal + 하급 루비","큐브조합 사용":"익셉 유니크 방어구 업글(Ko+최상급 다이아몬드)","쓰이는 룬워드 아이템":"웰쓰 (Wealth)","":""},{"TOP":"","이름":"Pul(21)","무기장착시":"+75% Damage To Demons, +100 Attack Rating Against Demons","기타 장착시":"+30% Enhanced Defense","룬업그레이드":"3*Lem + 하급 에메랄드","큐브조합 사용":"익셉 유니크 무기 업글                        익셉 레어 무기 업글","쓰이는 룬워드 아이템":"우울 (Gloom)","":""},{"TOP":"","이름":"Um(22)","무기장착시":"25% Chance of Open Wounds","기타 장착시":"All Resistances +15(Armor/Helms) +22(Shields)","룬업그레이드":"2*Pul + 하급 다이아몬드","큐브조합 사용":"익셉 레어 무기 업글","쓰이는 룬워드 아이템":"야수 (Beast)","":""},{"TOP":"","이름":"Mal(23)","무기장착시":"Prevent Monster Heal","기타 장착시":"Magic Damage Reduced By 7","룬업그레이드":"2*Um + 토파즈","큐브조합 사용":"","쓰이는 룬워드 아이템":"Venom (베놈)","":""},{"TOP":"","이름":"Ist(24)","무기장착시":"30% Better Chance of Getting Magic Items","기타 장착시":"25% Better Chance of Getting Magic Items","룬업그레이드":"2*Mal + 자수정","큐브조합 사용":"","쓰이는 룬워드 아이템":"침묵(Silence)","":""},{"TOP":"","이름":"Gul(25)","무기장착시":"20% Bonus To Attack Rating","기타 장착시":"5% To Maximum Poison Resist","룬업그레이드":"2*Ist + 사파이어","큐브조합 사용":"","쓰이는 룬워드 아이템":"원한(Fury)","":""},{"TOP":"","이름":"Vex(26)","무기장착시":"7% Mana Stolen Per Hit","기타 장착시":"5% To Maximum Fire Resist","룬업그레이드":"2*Gul + 루비","큐브조합 사용":"","쓰이는 룬워드 아이템":"침묵(Silence)","":""},{"TOP":"","이름":"Ohm(27)","무기장착시":"+50% Enhanced Damage","기타 장착시":"5% To Maximum Cold Resist","룬업그레이드":"2*Vex + 에메랄드","큐브조합 사용":"","쓰이는 룬워드 아이템":"검은 딸기 (Bramble)","":""},{"TOP":"","이름":"Lo(28)","무기장착시":"20% Deadly Strike","기타 장착시":"5% To Maximum Lightning Resist","룬업그레이드":"2*Ohm + 다이아몬드","큐브조합 사용":"","쓰이는 룬워드 아이템":"파멸 (Doom)","":""},{"TOP":"","이름":"Sur(29)","무기장착시":"Hit Blinds Target","기타 장착시":"Maximum Mana 5%/+50 To Mana (Shields)","룬업그레이드":"2*Lo + 상급 토파즈","큐브조합 사용":"","쓰이는 룬워드 아이템":"검은 딸기 (Bramble)","":""},{"TOP":"","이름":"Ber(30)","무기장착시":"20% Chance of Crushing Blow","기타 장착시":"Damage Reduced by 8%","룬업그레이드":"2*Sur + 상급 자수정","큐브조합 사용":"","쓰이는 룬워드 아이템":"야수 (Beast)","":""},{"TOP":"","이름":"Jah(31)","무기장착시":"Ignore Target's Defense","기타 장착시":"Increase Maximum Life 5%/+50 Life (Shields)","룬업그레이드":"2*Ber + 상급 사파이어","큐브조합 사용":"","쓰이는 룬워드 아이템":"원한(Fury)","":""},{"TOP":"","이름":"Cham(32)","무기장착시":"Freeze Target +3","기타 장착시":"Cannot Be Frozen","룬업그레이드":"2*Jah + 상급 루비","큐브조합 사용":"","쓰이는 룬워드 아이템":"파멸 (Doom)","":""},{"TOP":"","이름":"Zod(33)","무기장착시":"Indestructible","기타 장착시":"Indestructible","룬업그레이드":"2*Cham + 상급 에메랄드","큐브조합 사용":"","쓰이는 룬워드 아이템":"죽숨 (Breath of the Dying)","":""}]